mfd_ftp/__init__.py
mfd_ftp/client/__init__.py
mfd_ftp/client/__main__.py
mfd_ftp/client/ftp_client.py
mfd_ftp/server/__init__.py
mfd_ftp/server/__main__.py
mfd_ftp/server/ftp_server.py
mfd_ftp/traffics/__init__.py
mfd_ftp/traffics/base.py
mfd_ftp/traffics/client_traffic.py
mfd_ftp/traffics/server_traffic.py
mfd_ftp/util/__init__.py
mfd_ftp/util/base.py
mfd_ftp/util/exceptions.py
mfd_ftp-1.8.0.dist-info/licenses/AUTHORS.md
mfd_ftp-1.8.0.dist-info/licenses/LICENSE.md
mfd_ftp-1.8.0.dist-info/METADATA
mfd_ftp-1.8.0.dist-info/WHEEL
mfd_ftp-1.8.0.dist-info/top_level.txt
mfd_ftp-1.8.0.dist-info/RECORD
