Metadata-Version: 2.4
Name: mfd-ftp
Version: 1.8.0
Summary: Module for handling operations with File Transfer Protocol on client and server sessions.
Project-URL: Homepage, https://github.com/intel/mfd
Project-URL: Repository, https://github.com/intel/mfd-ftp
Project-URL: Issues, https://github.com/intel/mfd-ftp/issues
Project-URL: Changelog, https://github.com/intel/mfd-ftp/blob/main/CHANGELOG.md
Requires-Python: <3.14,>=3.10
License-File: LICENSE.md
License-File: AUTHORS.md
Requires-Dist: pyftpdlib~=1.5.6
Requires-Dist: mfd-common-libs>=1.11.0
Requires-Dist: mfd-typing>=1.23.0
Requires-Dist: mfd-traffic-manager>=1.18.0
Dynamic: license-file
